libq/__init__.py
libq/__version__.py
libq/base.py
libq/connections.py
libq/defaults.py
libq/errors.py
libq/job_store.py
libq/jobs.py
libq/logs.py
libq/queue.py
libq/scheduler.py
libq/serializers.py
libq/types.py
libq/utils.py
libq/worker.py
libq-0.7.4.dist-info/WHEEL
libq-0.7.4.dist-info/METADATA
libq-0.7.4.dist-info/RECORD
