Metadata-Version: 2.1
Name: libq
Version: 0.7.4
Summary: Simple async and sync queue system
Home-page: https://github.com/nuxion/libq
Keywords: queue,redis,async,distributed
Author: nuxion
Author-email: nuxion@gmail.com
Requires-Python: >=3.7,<3.11
Classifier: Programming Language :: Python :: 3
Classifier: Programming Language :: Python :: 3.10
Classifier: Programming Language :: Python :: 3.7
Classifier: Programming Language :: Python :: 3.8
Classifier: Programming Language :: Python :: 3.9
Requires-Dist: croniter (>=1.3.5,<2.0.0)
Requires-Dist: hiredis (>=2.0.0,<3.0.0)
Requires-Dist: nanoid (>=2.0.0,<3.0.0)
Requires-Dist: orjson (>=3.6.8,<4.0.0)
Requires-Dist: pydantic (>=1.9.0,<2.0.0)
Requires-Dist: redis (>=4.3.1,<5.0.0)
Requires-Dist: rich (>=12.4.1,<13.0.0)
Project-URL: Repository, https://github.com/nuxion/libq
